README.md
setup.cfg
setup.py
tf2utils/__init__.py
tf2utils/enums.py
tf2utils/market.py
tf2utils/marketplacetf.py
tf2utils/methods.py
tf2utils/pricestf.py
tf2utils/steam.py
tf2utils/tradetf.py
tf2utils.egg-info/PKG-INFO
tf2utils.egg-info/SOURCES.txt
tf2utils.egg-info/dependency_links.txt
tf2utils.egg-info/top_level.txt