Metadata-Version: 2.1
Name: tf2utils
Version: 1.0.0
Summary: Easily interact with multiple APIs associated with Team Fortress 2
Home-page: https://github.com/offish/tf2utils
Author: offish
Author-email: overutilization@gmail.com
License: UNKNOWN
Download-URL: https://github.com/offish/tf2utils/archive/v1.0.0.tar.gz
Platform: UNKNOWN
Classifier: Programming Language :: Python :: 3
Classifier: License :: OSI Approved :: MIT License
Classifier: Operating System :: OS Independent
Requires-Python: >=3.7
